dbt/adapters/odps/__init__.py
dbt/adapters/odps/__version__.py
dbt/adapters/odps/colums.py
dbt/adapters/odps/connections.py
dbt/adapters/odps/dbapi.py
dbt/adapters/odps/errors.py
dbt/adapters/odps/impl.py
dbt/adapters/odps/relation.py
dbt/adapters/odps/utils.py
dbt/include/odps/__init__.py
dbt/include/odps/dbt_project.yml
dbt/include/odps/profile_template.yml
dbt/include/odps/macros/adapters.sql
dbt/include/odps/macros/apply_grants.sql
dbt/include/odps/macros/materializations/seed.sql
dbt/include/odps/macros/materializations/snapshot.sql
dbt/include/odps/macros/materializations/table.sql
dbt/include/odps/macros/materializations/view.sql
dbt/include/odps/macros/materializations/incremental/incremental.sql
dbt/include/odps/macros/materializations/incremental/on_schema_change.sql
dbt/include/odps/macros/materializations/incremental/strategies.sql
dbt/include/odps/macros/materializations/incremental/validate.sql
dbt/include/odps/macros/utils/any_value.sql
dbt/include/odps/macros/utils/array_append.sql
dbt/include/odps/macros/utils/array_concat.sql
dbt/include/odps/macros/utils/array_construct.sql
dbt/include/odps/macros/utils/bool_or.sql
dbt/include/odps/macros/utils/cast_bool_to_text.sql
dbt/include/odps/macros/utils/concat.sql
dbt/include/odps/macros/utils/date_trunc.sql
dbt/include/odps/macros/utils/dateadd.sql
dbt/include/odps/macros/utils/datediff.sql
dbt/include/odps/macros/utils/escape_single_quotes.sql
dbt/include/odps/macros/utils/hash.sql
dbt/include/odps/macros/utils/last_day.sql
dbt/include/odps/macros/utils/listagg.sql
dbt/include/odps/macros/utils/position.sql
dbt/include/odps/macros/utils/right.sql
dbt/include/odps/macros/utils/split_part.sql
dbt/include/odps/macros/utils/timestamps.sql
winwin_odps_dbt-1.4.0.dist-info/METADATA
winwin_odps_dbt-1.4.0.dist-info/WHEEL
winwin_odps_dbt-1.4.0.dist-info/top_level.txt
winwin_odps_dbt-1.4.0.dist-info/RECORD
