Metadata-Version: 2.1
Name: winwin-odps-dbt
Version: 1.4.0
Summary: The ODPS (MaxCompute)  adapter plugin for dbt
Home-page: https://github.com/ai-excelsior/F2AI
Author: leezhongshan
Author-email: leezhongshan0316@gmail.com
Requires-Dist: dbt-core (~=1.4.0)
Requires-Dist: pyodps (~=0.11.4.1)
